dna_yolov4_torch/__init__.py
dna_yolov4_torch/cfg/yolov3-tiny.cfg
dna_yolov4_torch/cfg/yolov3.cfg
dna_yolov4_torch/cfg/yolov4-custom.cfg
dna_yolov4_torch/cfg/yolov4-tiny.cfg
dna_yolov4_torch/cfg/yolov4.cfg
dna_yolov4_torch/data/coco.names
dna_yolov4_torch/data/voc.names
dna_yolov4_torch/tool/__init__.py
dna_yolov4_torch/tool/camera.py
dna_yolov4_torch/tool/coco_annotation.py
dna_yolov4_torch/tool/config.py
dna_yolov4_torch/tool/darknet2onnx.py
dna_yolov4_torch/tool/darknet2pytorch.py
dna_yolov4_torch/tool/onnx2tensorflow.py
dna_yolov4_torch/tool/region_loss.py
dna_yolov4_torch/tool/torch_utils.py
dna_yolov4_torch/tool/utils.py
dna_yolov4_torch/tool/utils_iou.py
dna_yolov4_torch/tool/utils_iou_test.py
dna_yolov4_torch/tool/yolo_layer.py
dna_yolov4_torch-1.0.2.dist-info/METADATA
dna_yolov4_torch-1.0.2.dist-info/WHEEL
dna_yolov4_torch-1.0.2.dist-info/top_level.txt
dna_yolov4_torch-1.0.2.dist-info/RECORD
